{
"type": "FeatureCollection",
"crs": { "type": "name", "properties": { "name": "urn:ogc:def:crs:OGC:1.3:CRS84" } },
"features": [
{ "type": "Feature", "properties": { "year": "1750" }, "geometry": { "type": "Point", "coordinates": [ -78.73031, 40.86173 ] } },
{ "type": "Feature", "properties": { "year": "1751" }, "geometry": { "type": "Point", "coordinates": [ -78.73031, 40.86173 ] } },
{ "type": "Feature", "properties": { "year": "1752" }, "geometry": { "type": "Point", "coordinates": [ -78.73031, 40.86173 ] } },
{ "type": "Feature", "properties": { "year": "1752" }, "geometry": { "type": "Point", "coordinates": [ -81.43428, 40.3584 ] } },
{ "type": "Feature", "properties": { "year": "1753" }, "geometry": { "type": "Point", "coordinates": [ -78.73031, 40.86173 ] } },
{ "type": "Feature", "properties": { "year": "1753" }, "geometry": { "type": "Point", "coordinates": [ -78.73031, 40.86173 ] } },
{ "type": "Feature", "properties": { "year": "1754" }, "geometry": { "type": "Point", "coordinates": [ -75.99689, 39.95483 ] } },
{ "type": "Feature", "properties": { "year": "1754" }, "geometry": { "type": "Point", "coordinates": [ -75.99689, 39.95483 ] } },
{ "type": "Feature", "properties": { "year": "1754" }, "geometry": { "type": "Point", "coordinates": [ -81.43428, 40.3584 ] } },
{ "type": "Feature", "properties": { "year": "1755" }, "geometry": { "type": "Point", "coordinates": [ -81.43428, 40.3584 ] } },
{ "type": "Feature", "properties": { "year": "1764" }, "geometry": { "type": "Point", "coordinates": [ -75.16362, 39.95238 ] } }
]
}
