{
"type": "FeatureCollection",
"crs": { "type": "name", "properties": { "name": "urn:ogc:def:crs:OGC:1.3:CRS84" } },
"features": [
{ "type": "Feature", "properties": { "year": "1799" }, "geometry": { "type": "Point", "coordinates": [ -74.32432, 41.40204 ] } },
{ "type": "Feature", "properties": { "year": "1799" }, "geometry": { "type": "Point", "coordinates": [ -86.77718, 31.14101 ] } }
]
}
