{
"type": "FeatureCollection",
"crs": { "type": "name", "properties": { "name": "urn:ogc:def:crs:OGC:1.3:CRS84" } },
"features": [
{ "type": "Feature", "properties": { "year": "1742" }, "geometry": { "type": "Point", "coordinates": [ -73.59901, 41.92815 ] } },
{ "type": "Feature", "properties": { "year": "1742" }, "geometry": { "type": "Point", "coordinates": [ -73.59901, 41.92815 ] } },
{ "type": "Feature", "properties": { "year": "1742" }, "geometry": { "type": "Point", "coordinates": [ -73.59901, 41.92815 ] } },
{ "type": "Feature", "properties": { "year": "1742" }, "geometry": { "type": "Point", "coordinates": [ -73.59901, 41.92815 ] } },
{ "type": "Feature", "properties": { "year": "1742" }, "geometry": { "type": "Point", "coordinates": [ -75.4999, 43.00035 ] } },
{ "type": "Feature", "properties": { "year": "1742" }, "geometry": { "type": "Point", "coordinates": [ -78.73031, 40.86173 ] } },
{ "type": "Feature", "properties": { "year": "1743" }, "geometry": { "type": "Point", "coordinates": [ -73.59901, 41.92815 ] } },
{ "type": "Feature", "properties": { "year": "1743" }, "geometry": { "type": "Point", "coordinates": [ -73.59901, 41.92815 ] } },
{ "type": "Feature", "properties": { "year": "1743" }, "geometry": { "type": "Point", "coordinates": [ -73.59901, 41.92815 ] } },
{ "type": "Feature", "properties": { "year": "1743" }, "geometry": { "type": "Point", "coordinates": [ -73.59901, 41.92815 ] } },
{ "type": "Feature", "properties": { "year": "1743" }, "geometry": { "type": "Point", "coordinates": [ -73.59901, 41.92815 ] } },
{ "type": "Feature", "properties": { "year": "1743" }, "geometry": { "type": "Point", "coordinates": [ -73.91264, 41.92676 ] } },
{ "type": "Feature", "properties": { "year": "1743" }, "geometry": { "type": "Point", "coordinates": [ -75.16362, 39.95238 ] } },
{ "type": "Feature", "properties": { "year": "1743" }, "geometry": { "type": "Point", "coordinates": [ -75.16362, 39.95238 ] } },
{ "type": "Feature", "properties": { "year": "1743" }, "geometry": { "type": "Point", "coordinates": [ -75.16362, 39.95238 ] } },
{ "type": "Feature", "properties": { "year": "1743" }, "geometry": { "type": "Point", "coordinates": [ -75.4999, 43.00035 ] } },
{ "type": "Feature", "properties": { "year": "1744" }, "geometry": { "type": "Point", "coordinates": [ -73.59901, 41.92815 ] } },
{ "type": "Feature", "properties": { "year": "1744" }, "geometry": { "type": "Point", "coordinates": [ -73.59901, 41.92815 ] } },
{ "type": "Feature", "properties": { "year": "1744" }, "geometry": { "type": "Point", "coordinates": [ -73.59901, 41.92815 ] } },
{ "type": "Feature", "properties": { "year": "1744" }, "geometry": { "type": "Point", "coordinates": [ -73.91264, 41.92676 ] } },
{ "type": "Feature", "properties": { "year": "1744" }, "geometry": { "type": "Point", "coordinates": [ -73.91264, 41.92676 ] } },
{ "type": "Feature", "properties": { "year": "1744" }, "geometry": { "type": "Point", "coordinates": [ -73.91264, 41.92676 ] } },
{ "type": "Feature", "properties": { "year": "1744" }, "geometry": { "type": "Point", "coordinates": [ -73.91264, 41.92676 ] } },
{ "type": "Feature", "properties": { "year": "1744" }, "geometry": { "type": "Point", "coordinates": [ -73.92097, 41.70037 ] } },
{ "type": "Feature", "properties": { "year": "1744" }, "geometry": { "type": "Point", "coordinates": [ -73.92097, 41.70037 ] } },
{ "type": "Feature", "properties": { "year": "1744" }, "geometry": { "type": "Point", "coordinates": [ -73.92097, 41.70037 ] } },
{ "type": "Feature", "properties": { "year": "1744" }, "geometry": { "type": "Point", "coordinates": [ -73.96514, 41.82787 ] } },
{ "type": "Feature", "properties": { "year": "1744" }, "geometry": { "type": "Point", "coordinates": [ -78.73031, 40.86173 ] } },
{ "type": "Feature", "properties": { "year": "1744" }, "geometry": { "type": "Point", "coordinates": [ -78.73031, 40.86173 ] } },
{ "type": "Feature", "properties": { "year": "1744" }, "geometry": { "type": "Point", "coordinates": [ -78.73031, 40.86173 ] } },
{ "type": "Feature", "properties": { "year": "1744" }, "geometry": { "type": "Point", "coordinates": [ -78.73031, 40.86173 ] } },
{ "type": "Feature", "properties": { "year": "1744" }, "geometry": { "type": "Point", "coordinates": [ -81.5654, 39.73618 ] } }
]
}
