{
"type": "FeatureCollection",
"crs": { "type": "name", "properties": { "name": "urn:ogc:def:crs:OGC:1.3:CRS84" } },
"features": [
{ "type": "Feature", "properties": { "year": "1776" }, "geometry": { "type": "Point", "coordinates": [ -81.45818, 39.41619 ] } },
{ "type": "Feature", "properties": { "year": "1779" }, "geometry": { "type": "Point", "coordinates": [ -81.43428, 40.3584 ] } },
{ "type": "Feature", "properties": { "year": "1781" }, "geometry": { "type": "Point", "coordinates": [ -83.04575, 42.33143 ] } },
{ "type": "Feature", "properties": { "year": "1782" }, "geometry": { "type": "Point", "coordinates": [ -83.04575, 42.33143 ] } },
{ "type": "Feature", "properties": { "year": "1782" }, "geometry": { "type": "Point", "coordinates": [ -83.04575, 42.33143 ] } },
{ "type": "Feature", "properties": { "year": "1783" }, "geometry": { "type": "Point", "coordinates": [ -78.73031, 40.86173 ] } },
{ "type": "Feature", "properties": { "year": "1783" }, "geometry": { "type": "Point", "coordinates": [ -83.04575, 42.33143 ] } }
]
}
