{
"type": "FeatureCollection",
"crs": { "type": "name", "properties": { "name": "urn:ogc:def:crs:OGC:1.3:CRS84" } },
"features": [
{ "type": "Feature", "properties": { "year": "1804" }, "geometry": { "type": "Point", "coordinates": [ -82.54906, 41.3981 ] } },
{ "type": "Feature", "properties": { "year": "1805" }, "geometry": { "type": "Point", "coordinates": [ -83.45993, 41.69949 ] } }
]
}
