{
"type": "FeatureCollection",
"crs": { "type": "name", "properties": { "name": "urn:ogc:def:crs:OGC:1.3:CRS84" } },
"features": [
{ "type": "Feature", "properties": { "year": "1750" }, "geometry": { "type": "Point", "coordinates": [ -75.30962, 40.74038 ] } },
{ "type": "Feature", "properties": { "year": "1750" }, "geometry": { "type": "Point", "coordinates": [ -81.43428, 40.3584 ] } }
]
}
