{
"type": "FeatureCollection",
"crs": { "type": "name", "properties": { "name": "urn:ogc:def:crs:OGC:1.3:CRS84" } },
"features": [
{ "type": "Feature", "properties": { "year": "1801" }, "geometry": { "type": "Point", "coordinates": [ -53.21478, 47.49989 ] } },
{ "type": "Feature", "properties": { "year": "1801" }, "geometry": { "type": "Point", "coordinates": [ -74.32432, 41.40204 ] } },
{ "type": "Feature", "properties": { "year": "1801" }, "geometry": { "type": "Point", "coordinates": [ -81.43428, 40.3584 ] } },
{ "type": "Feature", "properties": { "year": "1802" }, "geometry": { "type": "Point", "coordinates": [ -74.32432, 41.40204 ] } },
{ "type": "Feature", "properties": { "year": "1806" }, "geometry": { "type": "Point", "coordinates": [ -74.32432, 41.40204 ] } },
{ "type": "Feature", "properties": { "year": "1806" }, "geometry": { "type": "Point", "coordinates": [ -78.73031, 40.86173 ] } },
{ "type": "Feature", "properties": { "year": "1807" }, "geometry": { "type": "Point", "coordinates": [ -74.32432, 41.40204 ] } },
{ "type": "Feature", "properties": { "year": "1807" }, "geometry": { "type": "Point", "coordinates": [ -75.30962, 40.74038 ] } },
{ "type": "Feature", "properties": { "year": "1807" }, "geometry": { "type": "Point", "coordinates": [ -81.43428, 40.3584 ] } },
{ "type": "Feature", "properties": { "year": "1807" }, "geometry": { "type": "Point", "coordinates": [ -81.43428, 40.3584 ] } },
{ "type": "Feature", "properties": { "year": "1807" }, "geometry": { "type": "Point", "coordinates": [ -81.43428, 40.3584 ] } },
{ "type": "Feature", "properties": { "year": "1808" }, "geometry": { "type": "Point", "coordinates": [ -74.32432, 41.40204 ] } },
{ "type": "Feature", "properties": { "year": "1808" }, "geometry": { "type": "Point", "coordinates": [ -74.32432, 41.40204 ] } },
{ "type": "Feature", "properties": { "year": "1808" }, "geometry": { "type": "Point", "coordinates": [ -74.32432, 41.40204 ] } },
{ "type": "Feature", "properties": { "year": "1808" }, "geometry": { "type": "Point", "coordinates": [ -85.12886, 41.1306 ] } },
{ "type": "Feature", "properties": { "year": "1808" }, "geometry": { "type": "Point", "coordinates": [ -85.12886, 41.1306 ] } },
{ "type": "Feature", "properties": { "year": "1808" }, "geometry": { "type": "Point", "coordinates": [ -88.03679, 46.90992 ] } },
{ "type": "Feature", "properties": { "year": "1808" }, "geometry": { "type": "Point", "coordinates": [ -88.03679, 46.90992 ] } },
{ "type": "Feature", "properties": { "year": "1809" }, "geometry": { "type": "Point", "coordinates": [ -73.26373, 41.14121 ] } },
{ "type": "Feature", "properties": { "year": "1809" }, "geometry": { "type": "Point", "coordinates": [ -74.32432, 41.40204 ] } },
{ "type": "Feature", "properties": { "year": "1809" }, "geometry": { "type": "Point", "coordinates": [ -81.43428, 40.3584 ] } },
{ "type": "Feature", "properties": { "year": "1809" }, "geometry": { "type": "Point", "coordinates": [ -82.54906, 41.3981 ] } },
{ "type": "Feature", "properties": { "year": "1809" }, "geometry": { "type": "Point", "coordinates": [ -82.54906, 41.3981 ] } },
{ "type": "Feature", "properties": { "year": "1810" }, "geometry": { "type": "Point", "coordinates": [ -81.44094, 42.82132 ] } },
{ "type": "Feature", "properties": { "year": "1810" }, "geometry": { "type": "Point", "coordinates": [ -82.70796, 41.44894 ] } },
{ "type": "Feature", "properties": { "year": "1811" }, "geometry": { "type": "Point", "coordinates": [ -82.70796, 41.44894 ] } },
{ "type": "Feature", "properties": { "year": "1812" }, "geometry": { "type": "Point", "coordinates": [ -74.32432, 41.40204 ] } },
{ "type": "Feature", "properties": { "year": "1812" }, "geometry": { "type": "Point", "coordinates": [ -81.43428, 40.3584 ] } },
{ "type": "Feature", "properties": { "year": "1812" }, "geometry": { "type": "Point", "coordinates": [ -81.44567, 40.48979 ] } },
{ "type": "Feature", "properties": { "year": "1813" }, "geometry": { "type": "Point", "coordinates": [ -81.43428, 40.3584 ] } },
{ "type": "Feature", "properties": { "year": "1813" }, "geometry": { "type": "Point", "coordinates": [ -81.43428, 40.3584 ] } },
{ "type": "Feature", "properties": { "year": "1813" }, "geometry": { "type": "Point", "coordinates": [ -81.44567, 40.48979 ] } },
{ "type": "Feature", "properties": { "year": "1814" }, "geometry": { "type": "Point", "coordinates": [ -81.43428, 40.3584 ] } },
{ "type": "Feature", "properties": { "year": "1814" }, "geometry": { "type": "Point", "coordinates": [ -81.43428, 40.3584 ] } },
{ "type": "Feature", "properties": { "year": "1814" }, "geometry": { "type": "Point", "coordinates": [ -86.52774, 31.24073 ] } }
]
}
