{
"type": "FeatureCollection",
"crs": { "type": "name", "properties": { "name": "urn:ogc:def:crs:OGC:1.3:CRS84" } },
"features": [
{ "type": "Feature", "properties": { "year": "1761" }, "geometry": { "type": "Point", "coordinates": [ -78.73031, 40.86173 ] } },
{ "type": "Feature", "properties": { "year": "1761" }, "geometry": { "type": "Point", "coordinates": [ -78.73031, 40.86173 ] } }
]
}
