{
"type": "FeatureCollection",
"crs": { "type": "name", "properties": { "name": "urn:ogc:def:crs:OGC:1.3:CRS84" } },
"features": [
{ "type": "Feature", "properties": { "year": "1743" }, "geometry": { "type": "Point", "coordinates": [ -73.59901, 41.92815 ] } },
{ "type": "Feature", "properties": { "year": "1744" }, "geometry": { "type": "Point", "coordinates": [ -78.73031, 40.86173 ] } },
{ "type": "Feature", "properties": { "year": "1745" }, "geometry": { "type": "Point", "coordinates": [ -73.91264, 41.92676 ] } },
{ "type": "Feature", "properties": { "year": "1746" }, "geometry": { "type": "Point", "coordinates": [ -73.59901, 41.92815 ] } },
{ "type": "Feature", "properties": { "year": "1746" }, "geometry": { "type": "Point", "coordinates": [ -73.59901, 41.92815 ] } },
{ "type": "Feature", "properties": { "year": "1746" }, "geometry": { "type": "Point", "coordinates": [ -73.59901, 41.92815 ] } }
]
}
