{
"type": "FeatureCollection",
"crs": { "type": "name", "properties": { "name": "urn:ogc:def:crs:OGC:1.3:CRS84" } },
"features": [
{ "type": "Feature", "properties": { "year": "1791" }, "geometry": { "type": "Point", "coordinates": [ -83.14986, 42.04116 ] } },
{ "type": "Feature", "properties": { "year": "1799" }, "geometry": { "type": "Point", "coordinates": [ -79.48201, 44.05502 ] } }
]
}
