{
"type": "FeatureCollection",
"crs": { "type": "name", "properties": { "name": "urn:ogc:def:crs:OGC:1.3:CRS84" } },
"features": [
{ "type": "Feature", "properties": { "year": "1803" }, "geometry": { "type": "Point", "coordinates": [ -73.26373, 41.14121 ] } },
{ "type": "Feature", "properties": { "year": "1812" }, "geometry": { "type": "Point", "coordinates": [ -74.32432, 41.40204 ] } },
{ "type": "Feature", "properties": { "year": "1812" }, "geometry": { "type": "Point", "coordinates": [ -81.31925, 35.03791 ] } }
]
}
