{
"type": "FeatureCollection",
"crs": { "type": "name", "properties": { "name": "urn:ogc:def:crs:OGC:1.3:CRS84" } },
"features": [
{ "type": "Feature", "properties": { "year": "1747" }, "geometry": { "type": "Point", "coordinates": [ -76.55885, 40.78897 ] } },
{ "type": "Feature", "properties": { "year": "1747" }, "geometry": { "type": "Point", "coordinates": [ -76.55885, 40.78897 ] } },
{ "type": "Feature", "properties": { "year": "1747" }, "geometry": { "type": "Point", "coordinates": [ -76.55885, 40.78897 ] } },
{ "type": "Feature", "properties": { "year": "1747" }, "geometry": { "type": "Point", "coordinates": [ -76.55885, 40.78897 ] } },
{ "type": "Feature", "properties": { "year": "1749" }, "geometry": { "type": "Point", "coordinates": [ -78.73031, 40.86173 ] } },
{ "type": "Feature", "properties": { "year": "1750" }, "geometry": { "type": "Point", "coordinates": [ -81.43428, 40.3584 ] } },
{ "type": "Feature", "properties": { "year": "1751" }, "geometry": { "type": "Point", "coordinates": [ -81.43428, 40.3584 ] } },
{ "type": "Feature", "properties": { "year": "1751" }, "geometry": { "type": "Point", "coordinates": [ -86.98636, 45.27262 ] } },
{ "type": "Feature", "properties": { "year": "1755" }, "geometry": { "type": "Point", "coordinates": [ -105.63666, 41.47747 ] } },
{ "type": "Feature", "properties": { "year": "1755" }, "geometry": { "type": "Point", "coordinates": [ -105.63666, 41.47747 ] } },
{ "type": "Feature", "properties": { "year": "1755" }, "geometry": { "type": "Point", "coordinates": [ -105.63666, 41.47747 ] } },
{ "type": "Feature", "properties": { "year": "1755" }, "geometry": { "type": "Point", "coordinates": [ -105.63666, 41.47747 ] } },
{ "type": "Feature", "properties": { "year": "1755" }, "geometry": { "type": "Point", "coordinates": [ -105.63666, 41.47747 ] } },
{ "type": "Feature", "properties": { "year": "1755" }, "geometry": { "type": "Point", "coordinates": [ -105.63666, 41.47747 ] } },
{ "type": "Feature", "properties": { "year": "1755" }, "geometry": { "type": "Point", "coordinates": [ -76.55885, 40.78897 ] } },
{ "type": "Feature", "properties": { "year": "1755" }, "geometry": { "type": "Point", "coordinates": [ -76.55885, 40.78897 ] } },
{ "type": "Feature", "properties": { "year": "1755" }, "geometry": { "type": "Point", "coordinates": [ -78.73031, 40.86173 ] } },
{ "type": "Feature", "properties": { "year": "1755" }, "geometry": { "type": "Point", "coordinates": [ -81.43428, 40.3584 ] } },
{ "type": "Feature", "properties": { "year": "1755" }, "geometry": { "type": "Point", "coordinates": [ -81.43428, 40.3584 ] } },
{ "type": "Feature", "properties": { "year": "1758" }, "geometry": { "type": "Point", "coordinates": [ -105.63666, 41.47747 ] } },
{ "type": "Feature", "properties": { "year": "1758" }, "geometry": { "type": "Point", "coordinates": [ -105.63666, 41.47747 ] } },
{ "type": "Feature", "properties": { "year": "1760" }, "geometry": { "type": "Point", "coordinates": [ -78.73031, 40.86173 ] } },
{ "type": "Feature", "properties": { "year": "1765" }, "geometry": { "type": "Point", "coordinates": [ -83.76132, 39.94145 ] } }
]
}
