{
"type": "FeatureCollection",
"crs": { "type": "name", "properties": { "name": "urn:ogc:def:crs:OGC:1.3:CRS84" } },
"features": [
{ "type": "Feature", "properties": { "year": "1750" }, "geometry": { "type": "Point", "coordinates": [ -81.43428, 40.3584 ] } },
{ "type": "Feature", "properties": { "year": "1753" }, "geometry": { "type": "Point", "coordinates": [ -73.42123, 41.98343 ] } },
{ "type": "Feature", "properties": { "year": "1753" }, "geometry": { "type": "Point", "coordinates": [ -73.74286, 41.76515 ] } },
{ "type": "Feature", "properties": { "year": "1753" }, "geometry": { "type": "Point", "coordinates": [ -73.91264, 41.92676 ] } },
{ "type": "Feature", "properties": { "year": "1753" }, "geometry": { "type": "Point", "coordinates": [ -78.73031, 40.86173 ] } }
]
}
