{
"type": "FeatureCollection",
"crs": { "type": "name", "properties": { "name": "urn:ogc:def:crs:OGC:1.3:CRS84" } },
"features": [
{ "type": "Feature", "properties": { "year": "1774" }, "geometry": { "type": "Point", "coordinates": [ -76.40302, 39.94677 ] } },
{ "type": "Feature", "properties": { "year": "1776" }, "geometry": { "type": "Point", "coordinates": [ -83.04575, 42.33143 ] } }
]
}
