{
"type": "FeatureCollection",
"crs": { "type": "name", "properties": { "name": "urn:ogc:def:crs:OGC:1.3:CRS84" } },
"features": [
{ "type": "Feature", "properties": { "year": "1806" }, "geometry": { "type": "Point", "coordinates": [ -73.38345, 41.3026 ] } },
{ "type": "Feature", "properties": { "year": "1808" }, "geometry": { "type": "Point", "coordinates": [ -81.43428, 40.3584 ] } },
{ "type": "Feature", "properties": { "year": "1808" }, "geometry": { "type": "Point", "coordinates": [ -81.43428, 40.3584 ] } },
{ "type": "Feature", "properties": { "year": "1809" }, "geometry": { "type": "Point", "coordinates": [ -74.32432, 41.40204 ] } },
{ "type": "Feature", "properties": { "year": "1809" }, "geometry": { "type": "Point", "coordinates": [ -76.3069, 40.15732 ] } },
{ "type": "Feature", "properties": { "year": "1809" }, "geometry": { "type": "Point", "coordinates": [ -81.43428, 40.3584 ] } },
{ "type": "Feature", "properties": { "year": "1809" }, "geometry": { "type": "Point", "coordinates": [ -81.43428, 40.3584 ] } }
]
}
